pythrottler/__init__.py
pythrottler/core.py
pythrottler-0.1.0.dist-info/METADATA
pythrottler-0.1.0.dist-info/WHEEL
pythrottler-0.1.0.dist-info/top_level.txt
pythrottler-0.1.0.dist-info/RECORD
